sunpower_pvs_exporter/__init__.py
sunpower_pvs_exporter/__main__.py
sunpower_pvs_exporter/exporter.py
sunpower_pvs_exporter-1.0.dist-info/LICENSE.md
sunpower_pvs_exporter-1.0.dist-info/METADATA
sunpower_pvs_exporter-1.0.dist-info/WHEEL
sunpower_pvs_exporter-1.0.dist-info/entry_points.txt
sunpower_pvs_exporter-1.0.dist-info/top_level.txt
sunpower_pvs_exporter-1.0.dist-info/RECORD
