Metadata-Version: 2.1
Name: sunpower-pvs-exporter
Version: 1.0
Summary: A Prometheus Exporter for the SunPower PVS Device
Home-page: https://github.com/ginoledesma/sunpower-pvs-exporter/
Author: Gino Ledesma
Author-email: gledesma@gmail.com
License: MIT
Keywords: sunpower pvs prometheus exporter
Platform: UNKNOWN
Classifier: Environment :: Console
Classifier: License :: OSI Approved :: MIT License
Classifier: Environment :: Web Environment
Classifier: Intended Audience :: Developers
Classifier: Programming Language :: Python :: 2
Classifier: Programming Language :: Python :: 2.7
Classifier: Programming Language :: Python :: 3
Classifier: Programming Language :: Python :: 3.4
Classifier: Programming Language :: Python :: 3.5
Classifier: Programming Language :: Python :: 3.6
Requires-Python: >=2.7
Requires-Dist: prometheus-client
Requires-Dist: requests
